orso_sample_builder/__init__.py
orso_sample_builder/__main__.py
orso_sample_builder/main_window.py
orso_sample_builder/model_editor.py
orso_sample_builder/ui_main_window.py
orso_tools/__init__.py
orso_tools/mpl_canvas.py
orso_tools/sample_viewer.py
orso_tools-0.3.3.dist-info/licenses/LICENSE
orso_viewer/__init__.py
orso_viewer/__main__.py
orso_viewer/main_window.py
orso_viewer/ui_main_window.py
orso_tools-0.3.3.dist-info/METADATA
orso_tools-0.3.3.dist-info/WHEEL
orso_tools-0.3.3.dist-info/entry_points.txt
orso_tools-0.3.3.dist-info/top_level.txt
orso_tools-0.3.3.dist-info/RECORD
