Metadata-Version: 2.4
Name: orso_tools
Version: 0.3.3
Summary: Tools for reflectometry from the Open Reflectometry Standards Organization (ORSO)
Home-page: https://github.com/reflectivity/orso_tools
Author: ORSO contributors (see AUTHORS.rst)
Author-email: artur.glavic@psi.ch
License: MIT
Classifier: Programming Language :: Python :: 3
Classifier: Operating System :: OS Independent
Classifier: Topic :: Scientific/Engineering
Classifier: Development Status :: 3 - Alpha
Requires-Python: >=3.9
License-File: LICENSE
Requires-Dist: PySide6
Requires-Dist: numpy
Requires-Dist: pyyaml
Requires-Dist: orsopy
Requires-Dist: matplotlib
Requires-Dist: refnx
Requires-Dist: pint
Dynamic: license-file
